CHANGES.rst
LICENSE.txt
MANIFEST.in
README.rst
requirements.txt
setup.py
awsebcli.egg-info/PKG-INFO
awsebcli.egg-info/SOURCES.txt
awsebcli.egg-info/dependency_links.txt
awsebcli.egg-info/entry_points.txt
awsebcli.egg-info/requires.txt
awsebcli.egg-info/top_level.txt
bin/__init__.py
bin/eb
ebcli/__init__.py
ebcli/bundled/__init__.py
ebcli/bundled/asciimatics/__init__.py
ebcli/bundled/asciimatics/event.py
ebcli/bundled/asciimatics/exceptions.py
ebcli/bundled/asciimatics/overrides.py
ebcli/bundled/asciimatics/screen.py
ebcli/bundled/asciimatics/utilities.py
ebcli/containers/__init__.py
ebcli/containers/abstractcontainer.py
ebcli/containers/commands.py
ebcli/containers/compat.py
ebcli/containers/compose.py
ebcli/containers/container_viewmodel.py
ebcli/containers/containerops.py
ebcli/containers/dockerrun.py
ebcli/containers/envvarcollector.py
ebcli/containers/factory.py
ebcli/containers/fshandler.py
ebcli/containers/generic_container.py
ebcli/containers/log.py
ebcli/containers/multicontainer.py
ebcli/containers/pathconfig.py
ebcli/containers/preconfigured_container.py
ebcli/containers/containerfiles/container_config.json
ebcli/containers/containerfiles/glassfish-runtime-4.0-jdk7
ebcli/containers/containerfiles/glassfish-runtime-4.1-jdk8
ebcli/containers/containerfiles/glassfish-runtime-5.0-al
ebcli/containers/containerfiles/golang-runtime-1.3
ebcli/containers/containerfiles/golang-runtime-1.4
ebcli/containers/containerfiles/python3-runtime
ebcli/controllers/__init__.py
ebcli/controllers/abort.py
ebcli/controllers/appversion.py
ebcli/controllers/clone.py
ebcli/controllers/codesource.py
ebcli/controllers/config.py
ebcli/controllers/console.py
ebcli/controllers/create.py
ebcli/controllers/deploy.py
ebcli/controllers/events.py
ebcli/controllers/health.py
ebcli/controllers/initialize.py
ebcli/controllers/lifecycle.py
ebcli/controllers/list.py
ebcli/controllers/local.py
ebcli/controllers/logs.py
ebcli/controllers/open.py
ebcli/controllers/printenv.py
ebcli/controllers/restore.py
ebcli/controllers/scale.py
ebcli/controllers/setenv.py
ebcli/controllers/ssh.py
ebcli/controllers/status.py
ebcli/controllers/swap.py
ebcli/controllers/tags.py
